{"soc_code":"51-4199","geo_type":"state","total":39,"limit":100,"offset":0,"wages":[{"geo_type":"state","geo_code":"01","geo_name":"Alabama","employment_count":180,"mean_annual_wage":56920.0,"median_annual_wage":59060.0,"mean_hourly_wage":27.37,"median_hourly_wage":28.4,"p10_hourly_wage":25.6,"p25_hourly_wage":28.16,"p75_hourly_wage":28.4,"p90_hourly_wage":28.4,"source_release_id":"2023.05","reference_period":"2023.05"},{"geo_type":"state","geo_code":"04","geo_name":"Arizona","employment_count":null,"mean_annual_wage":46490.0,"median_annual_wage":44610.0,"mean_hourly_wage":22.35,"median_hourly_wage":21.45,"p10_hourly_wage":19.1,"p25_hourly_wage":19.61,"p75_hourly_wage":23.21,"p90_hourly_wage":28.21,"source_release_id":"2023.05","reference_period":"2023.05"},{"geo_type":"state","geo_code":"05","geo_name":"Arkansas","employment_count":230,"mean_annual_wage":48830.0,"median_annual_wage":44000.0,"mean_hourly_wage":23.48,"median_hourly_wage":21.16,"p10_hourly_wage":16.28,"p25_hourly_wage":17.05,"p75_hourly_wage":28.8,"p90_hourly_wage":30.7,"source_release_id":"2023.05","reference_period":"2023.05"},{"geo_type":"state","geo_code":"06","geo_name":"California","employment_count":3320,"mean_annual_wage":45660.0,"median_annual_wage":41530.0,"mean_hourly_wage":21.95,"median_hourly_wage":19.97,"p10_hourly_wage":17.05,"p25_hourly_wage":18.23,"p75_hourly_wage":22.95,"p90_hourly_wage":30.01,"source_release_id":"2023.05","reference_period":"2023.05"},{"geo_type":"state","geo_code":"08","geo_name":"Colorado","employment_count":250,"mean_annual_wage":50020.0,"median_annual_wage":43220.0,"mean_hourly_wage":24.05,"median_hourly_wage":20.78,"p10_hourly_wage":17.0,"p25_hourly_wage":17.92,"p75_hourly_wage":27.49,"p90_hourly_wage":37.17,"source_release_id":"2023.05","reference_period":"2023.05"},{"geo_type":"state","geo_code":"09","geo_name":"Connecticut","employment_count":50,"mean_annual_wage":47600.0,"median_annual_wage":46580.0,"mean_hourly_wage":22.89,"median_hourly_wage":22.4,"p10_hourly_wage":15.85,"p25_hourly_wage":18.64,"p75_hourly_wage":24.96,"p90_hourly_wage":29.75,"source_release_id":"2023.05","reference_period":"2023.05"},{"geo_type":"state","geo_code":"12","geo_name":"Florida","employment_count":760,"mean_annual_wage":40590.0,"median_annual_wage":38570.0,"mean_hourly_wage":19.52,"median_hourly_wage":18.55,"p10_hourly_wage":14.93,"p25_hourly_wage":16.92,"p75_hourly_wage":21.6,"p90_hourly_wage":25.02,"source_release_id":"2023.05","reference_period":"2023.05"},{"geo_type":"state","geo_code":"13","geo_name":"Georgia","employment_count":1430,"mean_annual_wage":39930.0,"median_annual_wage":38280.0,"mean_hourly_wage":19.2,"median_hourly_wage":18.41,"p10_hourly_wage":15.0,"p25_hourly_wage":16.83,"p75_hourly_wage":21.53,"p90_hourly_wage":23.06,"source_release_id":"2023.05","reference_period":"2023.05"},{"geo_type":"state","geo_code":"17","geo_name":"Illinois","employment_count":500,"mean_annual_wage":49580.0,"median_annual_wage":47910.0,"mean_hourly_wage":23.84,"median_hourly_wage":23.04,"p10_hourly_wage":16.83,"p25_hourly_wage":21.1,"p75_hourly_wage":25.79,"p90_hourly_wage":30.54,"source_release_id":"2023.05","reference_period":"2023.05"},{"geo_type":"state","geo_code":"18","geo_name":"Indiana","employment_count":630,"mean_annual_wage":50890.0,"median_annual_wage":49620.0,"mean_hourly_wage":24.47,"median_hourly_wage":23.85,"p10_hourly_wage":18.23,"p25_hourly_wage":19.8,"p75_hourly_wage":28.48,"p90_hourly_wage":30.05,"source_release_id":"2023.05","reference_period":"2023.05"},{"geo_type":"state","geo_code":"19","geo_name":"Iowa","employment_count":90,"mean_annual_wage":42760.0,"median_annual_wage":41710.0,"mean_hourly_wage":20.56,"median_hourly_wage":20.05,"p10_hourly_wage":15.52,"p25_hourly_wage":17.05,"p75_hourly_wage":21.0,"p90_hourly_wage":24.89,"source_release_id":"2023.05","reference_period":"2023.05"},{"geo_type":"state","geo_code":"20","geo_name":"Kansas","employment_count":80,"mean_annual_wage":36870.0,"median_annual_wage":33520.0,"mean_hourly_wage":17.73,"median_hourly_wage":16.12,"p10_hourly_wage":14.47,"p25_hourly_wage":14.48,"p75_hourly_wage":17.49,"p90_hourly_wage":24.49,"source_release_id":"2023.05","reference_period":"2023.05"},{"geo_type":"state","geo_code":"21","geo_name":"Kentucky","employment_count":190,"mean_annual_wage":48130.0,"median_annual_wage":46470.0,"mean_hourly_wage":23.14,"median_hourly_wage":22.34,"p10_hourly_wage":13.84,"p25_hourly_wage":17.94,"p75_hourly_wage":30.48,"p90_hourly_wage":30.48,"source_release_id":"2023.05","reference_period":"2023.05"},{"geo_type":"state","geo_code":"22","geo_name":"Louisiana","employment_count":80,"mean_annual_wage":41290.0,"median_annual_wage":33270.0,"mean_hourly_wage":19.85,"median_hourly_wage":16.0,"p10_hourly_wage":13.42,"p25_hourly_wage":14.73,"p75_hourly_wage":25.38,"p90_hourly_wage":31.36,"source_release_id":"2023.05","reference_period":"2023.05"},{"geo_type":"state","geo_code":"23","geo_name":"Maine","employment_count":60,"mean_annual_wage":51730.0,"median_annual_wage":38500.0,"mean_hourly_wage":24.87,"median_hourly_wage":18.51,"p10_hourly_wage":16.11,"p25_hourly_wage":18.43,"p75_hourly_wage":33.77,"p90_hourly_wage":37.48,"source_release_id":"2023.05","reference_period":"2023.05"},{"geo_type":"state","geo_code":"24","geo_name":"Maryland","employment_count":250,"mean_annual_wage":45910.0,"median_annual_wage":41580.0,"mean_hourly_wage":22.07,"median_hourly_wage":19.99,"p10_hourly_wage":16.68,"p25_hourly_wage":18.0,"p75_hourly_wage":24.43,"p90_hourly_wage":32.6,"source_release_id":"2023.05","reference_period":"2023.05"},{"geo_type":"state","geo_code":"25","geo_name":"Massachusetts","employment_count":90,"mean_annual_wage":54380.0,"median_annual_wage":52580.0,"mean_hourly_wage":26.15,"median_hourly_wage":25.28,"p10_hourly_wage":19.32,"p25_hourly_wage":19.97,"p75_hourly_wage":26.98,"p90_hourly_wage":40.83,"source_release_id":"2023.05","reference_period":"2023.05"},{"geo_type":"state","geo_code":"26","geo_name":"Michigan","employment_count":940,"mean_annual_wage":42760.0,"median_annual_wage":37630.0,"mean_hourly_wage":20.56,"median_hourly_wage":18.09,"p10_hourly_wage":15.56,"p25_hourly_wage":16.81,"p75_hourly_wage":23.41,"p90_hourly_wage":29.18,"source_release_id":"2023.05","reference_period":"2023.05"},{"geo_type":"state","geo_code":"27","geo_name":"Minnesota","employment_count":280,"mean_annual_wage":42260.0,"median_annual_wage":39610.0,"mean_hourly_wage":20.32,"median_hourly_wage":19.04,"p10_hourly_wage":17.99,"p25_hourly_wage":18.89,"p75_hourly_wage":21.61,"p90_hourly_wage":22.96,"source_release_id":"2023.05","reference_period":"2023.05"},{"geo_type":"state","geo_code":"28","geo_name":"Mississippi","employment_count":40,"mean_annual_wage":48870.0,"median_annual_wage":45670.0,"mean_hourly_wage":23.49,"median_hourly_wage":21.96,"p10_hourly_wage":11.2,"p25_hourly_wage":15.53,"p75_hourly_wage":30.1,"p90_hourly_wage":35.84,"source_release_id":"2023.05","reference_period":"2023.05"},{"geo_type":"state","geo_code":"29","geo_name":"Missouri","employment_count":90,"mean_annual_wage":46780.0,"median_annual_wage":31150.0,"mean_hourly_wage":22.49,"median_hourly_wage":14.98,"p10_hourly_wage":14.59,"p25_hourly_wage":14.59,"p75_hourly_wage":38.77,"p90_hourly_wage":38.77,"source_release_id":"2023.05","reference_period":"2023.05"},{"geo_type":"state","geo_code":"30","geo_name":"Montana","employment_count":80,"mean_annual_wage":46270.0,"median_annual_wage":47920.0,"mean_hourly_wage":22.24,"median_hourly_wage":23.04,"p10_hourly_wage":14.93,"p25_hourly_wage":15.41,"p75_hourly_wage":25.06,"p90_hourly_wage":31.11,"source_release_id":"2023.05","reference_period":"2023.05"},{"geo_type":"state","geo_code":"32","geo_name":"Nevada","employment_count":470,"mean_annual_wage":45700.0,"median_annual_wage":44730.0,"mean_hourly_wage":21.97,"median_hourly_wage":21.5,"p10_hourly_wage":17.35,"p25_hourly_wage":17.91,"p75_hourly_wage":27.03,"p90_hourly_wage":29.06,"source_release_id":"2023.05","reference_period":"2023.05"},{"geo_type":"state","geo_code":"33","geo_name":"New Hampshire","employment_count":600,"mean_annual_wage":43810.0,"median_annual_wage":43020.0,"mean_hourly_wage":21.06,"median_hourly_wage":20.68,"p10_hourly_wage":16.77,"p25_hourly_wage":18.47,"p75_hourly_wage":22.57,"p90_hourly_wage":26.93,"source_release_id":"2023.05","reference_period":"2023.05"},{"geo_type":"state","geo_code":"34","geo_name":"New Jersey","employment_count":200,"mean_annual_wage":43010.0,"median_annual_wage":42340.0,"mean_hourly_wage":20.68,"median_hourly_wage":20.36,"p10_hourly_wage":15.36,"p25_hourly_wage":17.15,"p75_hourly_wage":22.85,"p90_hourly_wage":27.38,"source_release_id":"2023.05","reference_period":"2023.05"},{"geo_type":"state","geo_code":"36","geo_name":"New York","employment_count":210,"mean_annual_wage":52340.0,"median_annual_wage":43930.0,"mean_hourly_wage":25.16,"median_hourly_wage":21.12,"p10_hourly_wage":19.64,"p25_hourly_wage":19.83,"p75_hourly_wage":27.39,"p90_hourly_wage":36.36,"source_release_id":"2023.05","reference_period":"2023.05"},{"geo_type":"state","geo_code":"37","geo_name":"North Carolina","employment_count":340,"mean_annual_wage":45220.0,"median_annual_wage":38030.0,"mean_hourly_wage":21.74,"median_hourly_wage":18.29,"p10_hourly_wage":15.22,"p25_hourly_wage":17.16,"p75_hourly_wage":22.89,"p90_hourly_wage":35.74,"source_release_id":"2023.05","reference_period":"2023.05"},{"geo_type":"state","geo_code":"39","geo_name":"Ohio","employment_count":1980,"mean_annual_wage":44160.0,"median_annual_wage":41600.0,"mean_hourly_wage":21.23,"median_hourly_wage":20.0,"p10_hourly_wage":18.35,"p25_hourly_wage":18.7,"p75_hourly_wage":22.31,"p90_hourly_wage":27.27,"source_release_id":"2023.05","reference_period":"2023.05"},{"geo_type":"state","geo_code":"40","geo_name":"Oklahoma","employment_count":null,"mean_annual_wage":47390.0,"median_annual_wage":44850.0,"mean_hourly_wage":22.78,"median_hourly_wage":21.56,"p10_hourly_wage":13.32,"p25_hourly_wage":15.72,"p75_hourly_wage":30.29,"p90_hourly_wage":31.73,"source_release_id":"2023.05","reference_period":"2023.05"},{"geo_type":"state","geo_code":"41","geo_name":"Oregon","employment_count":480,"mean_annual_wage":50590.0,"median_annual_wage":46820.0,"mean_hourly_wage":24.32,"median_hourly_wage":22.51,"p10_hourly_wage":14.36,"p25_hourly_wage":17.06,"p75_hourly_wage":31.06,"p90_hourly_wage":37.49,"source_release_id":"2023.05","reference_period":"2023.05"},{"geo_type":"state","geo_code":"42","geo_name":"Pennsylvania","employment_count":960,"mean_annual_wage":46480.0,"median_annual_wage":48560.0,"mean_hourly_wage":22.34,"median_hourly_wage":23.35,"p10_hourly_wage":15.82,"p25_hourly_wage":17.47,"p75_hourly_wage":25.01,"p90_hourly_wage":28.92,"source_release_id":"2023.05","reference_period":"2023.05"},{"geo_type":"state","geo_code":"45","geo_name":"South Carolina","employment_count":200,"mean_annual_wage":46120.0,"median_annual_wage":46720.0,"mean_hourly_wage":22.18,"median_hourly_wage":22.46,"p10_hourly_wage":16.83,"p25_hourly_wage":19.34,"p75_hourly_wage":23.91,"p90_hourly_wage":27.9,"source_release_id":"2023.05","reference_period":"2023.05"},{"geo_type":"state","geo_code":"47","geo_name":"Tennessee","employment_count":850,"mean_annual_wage":41110.0,"median_annual_wage":39450.0,"mean_hourly_wage":19.76,"median_hourly_wage":18.97,"p10_hourly_wage":14.92,"p25_hourly_wage":16.8,"p75_hourly_wage":21.5,"p90_hourly_wage":24.97,"source_release_id":"2023.05","reference_period":"2023.05"},{"geo_type":"state","geo_code":"48","geo_name":"Texas","employment_count":2140,"mean_annual_wage":38830.0,"median_annual_wage":37600.0,"mean_hourly_wage":18.67,"median_hourly_wage":18.08,"p10_hourly_wage":14.84,"p25_hourly_wage":15.47,"p75_hourly_wage":20.0,"p90_hourly_wage":24.26,"source_release_id":"2023.05","reference_period":"2023.05"},{"geo_type":"state","geo_code":"49","geo_name":"Utah","employment_count":90,"mean_annual_wage":35690.0,"median_annual_wage":31740.0,"mean_hourly_wage":17.16,"median_hourly_wage":15.26,"p10_hourly_wage":13.99,"p25_hourly_wage":14.14,"p75_hourly_wage":17.17,"p90_hourly_wage":25.09,"source_release_id":"2023.05","reference_period":"2023.05"},{"geo_type":"state","geo_code":"50","geo_name":"Vermont","employment_count":60,"mean_annual_wage":39740.0,"median_annual_wage":37750.0,"mean_hourly_wage":19.11,"median_hourly_wage":18.15,"p10_hourly_wage":15.2,"p25_hourly_wage":15.65,"p75_hourly_wage":18.81,"p90_hourly_wage":30.97,"source_release_id":"2023.05","reference_period":"2023.05"},{"geo_type":"state","geo_code":"51","geo_name":"Virginia","employment_count":130,"mean_annual_wage":55910.0,"median_annual_wage":51810.0,"mean_hourly_wage":26.88,"median_hourly_wage":24.91,"p10_hourly_wage":17.45,"p25_hourly_wage":19.33,"p75_hourly_wage":36.56,"p90_hourly_wage":36.56,"source_release_id":"2023.05","reference_period":"2023.05"},{"geo_type":"state","geo_code":"53","geo_name":"Washington","employment_count":500,"mean_annual_wage":61970.0,"median_annual_wage":51500.0,"mean_hourly_wage":29.8,"median_hourly_wage":24.76,"p10_hourly_wage":15.96,"p25_hourly_wage":20.26,"p75_hourly_wage":44.46,"p90_hourly_wage":47.22,"source_release_id":"2023.05","reference_period":"2023.05"},{"geo_type":"state","geo_code":"55","geo_name":"Wisconsin","employment_count":720,"mean_annual_wage":41920.0,"median_annual_wage":38900.0,"mean_hourly_wage":20.16,"median_hourly_wage":18.7,"p10_hourly_wage":17.66,"p25_hourly_wage":17.88,"p75_hourly_wage":20.66,"p90_hourly_wage":25.22,"source_release_id":"2023.05","reference_period":"2023.05"}]}