{"soc_code":"17-1000","occupation_title":"Architects, Surveyors, and Cartographers","occupation_level":2,"occupation_level_name":"minor_group","parent_soc_code":"17-0000","major_group_code":"17-0000","minor_group_code":"17-1000","broad_occupation_code":null,"detailed_occupation_code":null,"occupation_definition":"","soc_version":"2018","is_leaf":false,"source_release_id":"2018","breadcrumb":[{"soc_code":"17-0000","occupation_title":"Architecture and Engineering Occupations"},{"soc_code":"17-1000","occupation_title":"Architects, Surveyors, and Cartographers"}],"siblings":[{"soc_code":"17-2000","occupation_title":"Engineers"},{"soc_code":"17-3000","occupation_title":"Drafters, Engineering Technicians, and Mapping Technicians"}],"children":[{"soc_code":"17-1010","occupation_title":"Architects, Except Naval"},{"soc_code":"17-1020","occupation_title":"Surveyors, Cartographers, and Photogrammetrists"}]}