{"soc_code":"19-4099","occupation_title":"Life, Physical, and Social Science Technicians, All Other","occupation_level":4,"occupation_level_name":"detailed_occupation","parent_soc_code":"19-4090","major_group_code":"19-0000","minor_group_code":"19-4000","broad_occupation_code":"19-4090","detailed_occupation_code":"19-4099","occupation_definition":"All life, physical, and social science technicians not listed separately.","soc_version":"2018","is_leaf":true,"source_release_id":"2018","breadcrumb":[{"soc_code":"19-0000","occupation_title":"Life, Physical, and Social Science Occupations"},{"soc_code":"19-4000","occupation_title":"Life, Physical, and Social Science Technicians"},{"soc_code":"19-4090","occupation_title":"Miscellaneous Life, Physical, and Social Science Technicians"},{"soc_code":"19-4099","occupation_title":"Life, Physical, and Social Science Technicians, All Other"}],"siblings":[{"soc_code":"19-4092","occupation_title":"Forensic Science Technicians"}],"children":[]}