{"soc_code":"29-9093","occupation_title":"Surgical Assistants","occupation_level":4,"occupation_level_name":"detailed_occupation","parent_soc_code":"29-9090","major_group_code":"29-0000","minor_group_code":"29-9000","broad_occupation_code":"29-9090","detailed_occupation_code":"29-9093","occupation_definition":"Assist in operations, under the supervision of surgeons. May, in accordance with state laws, help surgeons to make incisions and close surgical sites, manipulate or remove tissues, implant surgical devices or drains, suction the surgical site, place catheters, clamp or cauterize vessels or tissue, and apply dressings to surgical site. Excludes “Registered Nurses” (29-1141) and “Surgical Technologists” (29-2055).","soc_version":"2018","is_leaf":true,"source_release_id":"2018","breadcrumb":[{"soc_code":"29-0000","occupation_title":"Healthcare Practitioners and Technical Occupations"},{"soc_code":"29-9000","occupation_title":"Other Healthcare Practitioners and Technical Occupations"},{"soc_code":"29-9090","occupation_title":"Miscellaneous Health Practitioners and Technical Workers"},{"soc_code":"29-9093","occupation_title":"Surgical Assistants"}],"siblings":[{"soc_code":"29-9091","occupation_title":"Athletic Trainers"},{"soc_code":"29-9092","occupation_title":"Genetic Counselors"},{"soc_code":"29-9099","occupation_title":"Healthcare Practitioners and Technical Workers, All Other"}],"children":[]}