{"soc_code":"47-2161","similar":[{"soc_code":"47-2132","occupation_title":"Insulation Workers, Mechanical","similarity_score":0.9949},{"soc_code":"47-2041","occupation_title":"Carpet Installers","similarity_score":0.9948},{"soc_code":"51-7021","occupation_title":"Furniture Finishers","similarity_score":0.9946},{"soc_code":"47-2221","occupation_title":"Structural Iron and Steel Workers","similarity_score":0.9945},{"soc_code":"49-9095","occupation_title":"Manufactured Building and Mobile Home Installers","similarity_score":0.9941},{"soc_code":"47-2181","occupation_title":"Roofers","similarity_score":0.9941},{"soc_code":"47-2131","occupation_title":"Insulation Workers, Floor, Ceiling, and Wall","similarity_score":0.994},{"soc_code":"47-2031","occupation_title":"Carpenters","similarity_score":0.9938},{"soc_code":"47-1011","occupation_title":"First-Line Supervisors of Construction Trades and Extraction Workers","similarity_score":0.9936},{"soc_code":"47-2121","occupation_title":"Glaziers","similarity_score":0.9934}]}