{"member_code":"SS45011","siblings":[{"member_code":"SS4501A","title":"New cars and trucks","hierarchy_level":"Item stratum","semantic_role":"average_price_item"},{"member_code":"SS45021","title":"New trucks","hierarchy_level":"Item stratum","semantic_role":"average_price_item"},{"member_code":"SS45031","title":"New motorcycles","hierarchy_level":"Item stratum","semantic_role":"average_price_item"},{"member_code":"SS47014","title":"Gasoline, unleaded regular","hierarchy_level":"Item stratum","semantic_role":"average_price_item"},{"member_code":"SS47015","title":"Gasoline, unleaded midgrade","hierarchy_level":"Item stratum","semantic_role":"average_price_item"},{"member_code":"SS47016","title":"Gasoline, unleaded premium","hierarchy_level":"Item stratum","semantic_role":"average_price_item"},{"member_code":"SS47021","title":"Motor oil, coolant, and fluids","hierarchy_level":"Item stratum","semantic_role":"average_price_item"},{"member_code":"SS48021","title":"Vehicle parts and equipment other than tires","hierarchy_level":"Item stratum","semantic_role":"average_price_item"},{"member_code":"SS52051","title":"Parking fees and tolls","hierarchy_level":"Item stratum","semantic_role":"average_price_item"}]}