{"soc_code":"39-6011","similar":[{"soc_code":"35-3023","occupation_title":"Fast Food and Counter Workers","similarity_score":0.9958},{"soc_code":"53-6021","occupation_title":"Parking Attendants","similarity_score":0.9949},{"soc_code":"41-2021","occupation_title":"Counter and Rental Clerks","similarity_score":0.9945},{"soc_code":"39-3091","occupation_title":"Amusement and Recreation Attendants","similarity_score":0.9938},{"soc_code":"39-4021","occupation_title":"Funeral Attendants","similarity_score":0.9936},{"soc_code":"35-2021","occupation_title":"Food Preparation Workers","similarity_score":0.9935},{"soc_code":"53-3031","occupation_title":"Driver/Sales Workers","similarity_score":0.9933},{"soc_code":"43-5021","occupation_title":"Couriers and Messengers","similarity_score":0.9929},{"soc_code":"53-7065","occupation_title":"Stockers and Order Fillers","similarity_score":0.9925},{"soc_code":"37-2012","occupation_title":"Maids and Housekeeping Cleaners","similarity_score":0.9924}]}