{"soc_code":"43-9031","metric":"mean_annual_wage","year":2023,"geographies":[{"geo_name":"Alabama","geo_code":"01","value":35650.0,"source_release_id":"2023.05"},{"geo_name":"Arizona","geo_code":"04","value":52250.0,"source_release_id":"2023.05"},{"geo_name":"California","geo_code":"06","value":71450.0,"source_release_id":"2023.05"},{"geo_name":"Colorado","geo_code":"08","value":69750.0,"source_release_id":"2023.05"},{"geo_name":"Florida","geo_code":"12","value":55960.0,"source_release_id":"2023.05"},{"geo_name":"Georgia","geo_code":"13","value":51890.0,"source_release_id":"2023.05"},{"geo_name":"Illinois","geo_code":"17","value":50180.0,"source_release_id":"2023.05"},{"geo_name":"Indiana","geo_code":"18","value":44880.0,"source_release_id":"2023.05"},{"geo_name":"Iowa","geo_code":"19","value":44990.0,"source_release_id":"2023.05"},{"geo_name":"Kentucky","geo_code":"21","value":40160.0,"source_release_id":"2023.05"},{"geo_name":"Maine","geo_code":"23","value":49640.0,"source_release_id":"2023.05"},{"geo_name":"Maryland","geo_code":"24","value":null,"source_release_id":"2023.05"},{"geo_name":"Massachusetts","geo_code":"25","value":61620.0,"source_release_id":"2023.05"},{"geo_name":"Minnesota","geo_code":"27","value":60480.0,"source_release_id":"2023.05"},{"geo_name":"Nebraska","geo_code":"31","value":34580.0,"source_release_id":"2023.05"},{"geo_name":"New Jersey","geo_code":"34","value":53930.0,"source_release_id":"2023.05"},{"geo_name":"New York","geo_code":"36","value":80010.0,"source_release_id":"2023.05"},{"geo_name":"North Carolina","geo_code":"37","value":49260.0,"source_release_id":"2023.05"},{"geo_name":"Ohio","geo_code":"39","value":48400.0,"source_release_id":"2023.05"},{"geo_name":"Oklahoma","geo_code":"40","value":47930.0,"source_release_id":"2023.05"},{"geo_name":"Oregon","geo_code":"41","value":59400.0,"source_release_id":"2023.05"},{"geo_name":"Pennsylvania","geo_code":"42","value":53100.0,"source_release_id":"2023.05"},{"geo_name":"South Carolina","geo_code":"45","value":49370.0,"source_release_id":"2023.05"},{"geo_name":"Tennessee","geo_code":"47","value":37130.0,"source_release_id":"2023.05"},{"geo_name":"Texas","geo_code":"48","value":41400.0,"source_release_id":"2023.05"},{"geo_name":"Utah","geo_code":"49","value":null,"source_release_id":"2023.05"},{"geo_name":"Virginia","geo_code":"51","value":67140.0,"source_release_id":"2023.05"},{"geo_name":"Washington","geo_code":"53","value":71920.0,"source_release_id":"2023.05"},{"geo_name":"Wisconsin","geo_code":"55","value":null,"source_release_id":"2023.05"}]}