{"soc_code":"51-4194","metric":"mean_annual_wage","year":2023,"geographies":[{"geo_name":"Alabama","geo_code":"01","value":41500.0,"source_release_id":"2023.05"},{"geo_name":"Arkansas","geo_code":"05","value":43570.0,"source_release_id":"2023.05"},{"geo_name":"California","geo_code":"06","value":51000.0,"source_release_id":"2023.05"},{"geo_name":"Colorado","geo_code":"08","value":56880.0,"source_release_id":"2023.05"},{"geo_name":"Florida","geo_code":"12","value":40820.0,"source_release_id":"2023.05"},{"geo_name":"Georgia","geo_code":"13","value":47370.0,"source_release_id":"2023.05"},{"geo_name":"Idaho","geo_code":"16","value":51520.0,"source_release_id":"2023.05"},{"geo_name":"Indiana","geo_code":"18","value":45480.0,"source_release_id":"2023.05"},{"geo_name":"Iowa","geo_code":"19","value":52410.0,"source_release_id":"2023.05"},{"geo_name":"Kansas","geo_code":"20","value":45060.0,"source_release_id":"2023.05"},{"geo_name":"Kentucky","geo_code":"21","value":42080.0,"source_release_id":"2023.05"},{"geo_name":"Louisiana","geo_code":"22","value":49240.0,"source_release_id":"2023.05"},{"geo_name":"Massachusetts","geo_code":"25","value":51870.0,"source_release_id":"2023.05"},{"geo_name":"Michigan","geo_code":"26","value":45710.0,"source_release_id":"2023.05"},{"geo_name":"Minnesota","geo_code":"27","value":54910.0,"source_release_id":"2023.05"},{"geo_name":"Mississippi","geo_code":"28","value":36760.0,"source_release_id":"2023.05"},{"geo_name":"Missouri","geo_code":"29","value":49140.0,"source_release_id":"2023.05"},{"geo_name":"New Hampshire","geo_code":"33","value":44530.0,"source_release_id":"2023.05"},{"geo_name":"New Jersey","geo_code":"34","value":46910.0,"source_release_id":"2023.05"},{"geo_name":"New York","geo_code":"36","value":40660.0,"source_release_id":"2023.05"},{"geo_name":"North Carolina","geo_code":"37","value":45160.0,"source_release_id":"2023.05"},{"geo_name":"Ohio","geo_code":"39","value":54830.0,"source_release_id":"2023.05"},{"geo_name":"Oklahoma","geo_code":"40","value":43020.0,"source_release_id":"2023.05"},{"geo_name":"Oregon","geo_code":"41","value":60880.0,"source_release_id":"2023.05"},{"geo_name":"Pennsylvania","geo_code":"42","value":44030.0,"source_release_id":"2023.05"},{"geo_name":"South Carolina","geo_code":"45","value":46870.0,"source_release_id":"2023.05"},{"geo_name":"Tennessee","geo_code":"47","value":42430.0,"source_release_id":"2023.05"},{"geo_name":"Texas","geo_code":"48","value":38420.0,"source_release_id":"2023.05"},{"geo_name":"Virginia","geo_code":"51","value":38080.0,"source_release_id":"2023.05"},{"geo_name":"Washington","geo_code":"53","value":70970.0,"source_release_id":"2023.05"},{"geo_name":"Wisconsin","geo_code":"55","value":44310.0,"source_release_id":"2023.05"}]}