{"soc_code":"47-5044","metric":"mean_annual_wage","year":2023,"geographies":[{"geo_name":"Arizona","geo_code":"04","value":52300.0,"source_release_id":"2023.05"},{"geo_name":"Colorado","geo_code":"08","value":68920.0,"source_release_id":"2023.05"},{"geo_name":"Florida","geo_code":"12","value":42190.0,"source_release_id":"2023.05"},{"geo_name":"Georgia","geo_code":"13","value":51570.0,"source_release_id":"2023.05"},{"geo_name":"Illinois","geo_code":"17","value":73210.0,"source_release_id":"2023.05"},{"geo_name":"Iowa","geo_code":"19","value":50930.0,"source_release_id":"2023.05"},{"geo_name":"Kentucky","geo_code":"21","value":60650.0,"source_release_id":"2023.05"},{"geo_name":"Missouri","geo_code":"29","value":41170.0,"source_release_id":"2023.05"},{"geo_name":"Nevada","geo_code":"32","value":69880.0,"source_release_id":"2023.05"},{"geo_name":"New York","geo_code":"36","value":57650.0,"source_release_id":"2023.05"},{"geo_name":"North Carolina","geo_code":"37","value":45210.0,"source_release_id":"2023.05"},{"geo_name":"Ohio","geo_code":"39","value":39710.0,"source_release_id":"2023.05"},{"geo_name":"Oklahoma","geo_code":"40","value":42050.0,"source_release_id":"2023.05"},{"geo_name":"Pennsylvania","geo_code":"42","value":66050.0,"source_release_id":"2023.05"},{"geo_name":"Utah","geo_code":"49","value":64470.0,"source_release_id":"2023.05"},{"geo_name":"Virginia","geo_code":"51","value":67790.0,"source_release_id":"2023.05"},{"geo_name":"West Virginia","geo_code":"54","value":67030.0,"source_release_id":"2023.05"},{"geo_name":"Wyoming","geo_code":"56","value":93390.0,"source_release_id":"2023.05"}]}